[
  {
    "title": "一個美麗的夏日",
    "views": 100
  },
  {
    "title": "追尋幸福的旅程",
    "views": 200
  },
  {
    "title": "探索神秘的古城",
    "views": 300
  },
  {
    "title": "美食之旅：品味風味獨特的料理",
    "views": 400
  },
  {
    "title": "藝術與創意的世界",
    "views": 500
  },
  {
    "title": "挑戰極限：攀登高山之旅",
    "views": 600
  },
  {
    "title": "浪漫之都：夜色下的愛情故事",
    "views": 700
  },
  {
    "title": "探索海底奇觀：潛水冒險之旅",
    "views": 800
  },
  {
    "title": "寧靜與平衡：瑜伽修行之旅",
    "views": 900
  },
  {
    "title": "遺世獨立：寫作與創作的時光",
    "views": null
  }
]